redid_tools
