Metadata-Version: 1.1
Name: redid-tools
Version: 0.1.8
Summary: Redid media distribituion network tools. Redid provides a media distribution network offering dynamic media transformations and signed resource access.
Home-page: https://pypi.python.org/pypi/redid_tools
Author: edA-qa mort-ora-y
Author-email: eda-qa@disemia.com
License: MIT
Platform: UNKNOWN
Classifier: Development Status :: 3 - Alpha
Classifier: Programming Language :: Python
Classifier: Intended Audience :: Developers
Classifier: Environment :: Console
Classifier: License :: OSI Approved :: MIT License
Classifier: Operating System :: OS Independent
Classifier: Topic :: Internet :: WWW/HTTP
Classifier: Topic :: Internet :: WWW/HTTP :: Dynamic Content
Classifier: Topic :: Multimedia :: Graphics
